wapiti_swagger/__init__.py
wapiti_swagger/models.py
wapiti_swagger/parser.py
wapiti_swagger-0.1.9.dist-info/licenses/LICENSE
wapiti_swagger-0.1.9.dist-info/METADATA
wapiti_swagger-0.1.9.dist-info/WHEEL
wapiti_swagger-0.1.9.dist-info/top_level.txt
wapiti_swagger-0.1.9.dist-info/RECORD
