Metadata-Version: 2.4
Name: wapiti-swagger
Version: 0.1.9
Summary: A library for parsing and generating request bodies from Swagger/OpenAPI specifications.
Author-email: Nicolas Surribas <nicolas.surribas@gmail.com>
License: MIT
Keywords: swagger,openapi,wapiti,parser
Classifier: Programming Language :: Python :: 3
Classifier: License :: OSI Approved :: MIT License
Classifier: Operating System :: OS Independent
Classifier: Topic :: Software Development :: Libraries
Classifier: Topic :: Internet :: WWW/HTTP
Requires-Python: >=3.9
License-File: LICENSE
Requires-Dist: PyYAML>=6.0
Dynamic: license-file
